garpix_qa/MANIFEST.in
garpix_qa/README.md
garpix_qa/README.rst
garpix_qa/__init__.py
garpix_qa/apps.py
garpix_qa/checks.py
garpix_qa/colors.py
garpix_qa/constants.py
garpix_qa/helpers.py
garpix_qa/main.py
garpix_qa/setup.py
garpix_qa/__pycache__/__init__.cpython-38.pyc
garpix_qa/__pycache__/checks.cpython-38.pyc
garpix_qa/__pycache__/colors.cpython-38.pyc
garpix_qa/__pycache__/constants.cpython-38.pyc
garpix_qa/__pycache__/helpers.cpython-38.pyc
garpix_qa/__pycache__/main.cpython-38.pyc
garpix_qa/management/__init__.py
garpix_qa/management/__pycache__/__init__.cpython-38.pyc
garpix_qa/management/commands/__init__.py
garpix_qa/management/commands/qa.py
garpix_qa/management/commands/__pycache__/__init__.cpython-38.pyc
garpix_qa/management/commands/__pycache__/qa.cpython-38.pyc
garpix_qa-1.10.0.dist-info/METADATA
garpix_qa-1.10.0.dist-info/WHEEL
garpix_qa-1.10.0.dist-info/top_level.txt
garpix_qa-1.10.0.dist-info/RECORD
