Metadata-Version: 2.1
Name: garpix-qa
Version: 1.10.0
Summary: Checking the Django project for quality
Home-page: https://github.com/garpixcms/garpix_qa
Author: Garpix LTD
Author-email: info@garpix.com
License: MIT
Platform: UNKNOWN
Classifier: Development Status :: 4 - Beta
Classifier: Environment :: Web Environment
Classifier: Intended Audience :: Developers
Classifier: License :: OSI Approved :: MIT License
Classifier: Operating System :: OS Independent
Classifier: Programming Language :: Python
Classifier: Framework :: Django
Classifier: Programming Language :: Python :: 3.6
Classifier: Programming Language :: Python :: 3.7
Classifier: Programming Language :: Python :: 3.8
Requires-Dist: Django (>=1.11)
Requires-Dist: flake8 (>=3.8.4)
Requires-Dist: flake8-polyfill (>=1.0.2)
Requires-Dist: radon (>=4.3.2)
Requires-Dist: bandit (>=1.7.0)
